{
  "type": "minecraft:crafting_shaped",
  "category": "misc",
  "pattern": [
    "  s",
    " s ",
    "s  "
  ],
  "key": {
    "s": [
      "minecraft:stick"
    ]
  },
  "result": {
    "id": "minecraft:potion",
    "components": {
      "minecraft:potion_contents": {
        "custom_color": 2042561,
        "custom_name": "po",
        "custom_effects": [
          {
            "id": "minecraft:haste",
            "amplifier": 1,
            "duration": 2000,
            "show_particles": true,
            "show_icon": true
          }
        ]
      }
    },
    "count": 1
  }
}